automation_api/__init__.py
automation_api/api.py
automation_api/utils/__init__.py
automation_api/utils/dcm.py
automation_api/utils/mongodb.py
automation_api_deffets-0.0.12.dist-info/LICENSE
automation_api_deffets-0.0.12.dist-info/METADATA
automation_api_deffets-0.0.12.dist-info/WHEEL
automation_api_deffets-0.0.12.dist-info/top_level.txt
automation_api_deffets-0.0.12.dist-info/RECORD
