Metadata-Version: 2.1
Name: automation-api-deffets
Version: 0.0.12
Summary: Python API for the automation server database
Home-page: https://gitlab.com/deffets/automation/
Author: Sylvain Deffet
License: apache-2.0
Platform: UNKNOWN
Classifier: Programming Language :: Python :: 3
Classifier: Operating System :: OS Independent
Requires-Python: >=3.6
